hetu_pycli/__init__.py
hetu_pycli/cli.py
hetu_pycli/config.py
hetu_pycli/src/__init__.py
hetu_pycli/src/commands/config.py
hetu_pycli/src/commands/contract.py
hetu_pycli/src/commands/tx.py
hetu_pycli/src/commands/wallet.py
hetu_pycli/src/hetu/__init__.py
hetu_pycli/src/hetu/amm.py
hetu_pycli/src/hetu/erc20.py
hetu_pycli/src/hetu/neuron.py
hetu_pycli/src/hetu/staking.py
hetu_pycli/src/hetu/subnet.py
hetu_pycli/src/hetu/whetu.py
hetu_pycli/src/hetu/wrapper/erc20.py
hetu_pycli/src/hetu/wrapper/global_staking.py
hetu_pycli/src/hetu/wrapper/neuron_mgr.py
hetu_pycli/src/hetu/wrapper/subnet_amm.py
hetu_pycli/src/hetu/wrapper/subnet_mgr.py
hetu_pycli/src/hetu/wrapper/whetu.py
hetu_pycli/version.py
hetu_pycli-0.1.2.dist-info/LICENSE
hetu_pycli-0.1.2.dist-info/METADATA
hetu_pycli-0.1.2.dist-info/WHEEL
hetu_pycli-0.1.2.dist-info/entry_points.txt
hetu_pycli-0.1.2.dist-info/RECORD
