Metadata-Version: 2.1
Name: hetu-pycli
Version: 0.1.2
Summary: A command-line interface for Hetu Chain interactions
Home-page: https://github.com/hetu-project/hetu-pycli
Author: Hetu Protocol
Requires-Python: >=3.12,<4.0
Classifier: Programming Language :: Python :: 3
Classifier: Programming Language :: Python :: 3.12
Classifier: Programming Language :: Python :: 3.13
Requires-Dist: pytest (>=8.4.1,<9.0.0)
Requires-Dist: pyyaml (>=6.0.2,<7.0.0)
Requires-Dist: requests (>=2.31.0,<3.0.0)
Requires-Dist: rich (>=14.0.0,<15.0.0)
Requires-Dist: twine (>=6.1.0,<7.0.0)
Requires-Dist: typer (>=0.16.0,<0.17.0)
Requires-Dist: web3 (>=7.12.0,<8.0.0)
